discapty/__init__.py
discapty/captcha.py
discapty/captcha_queue.py
discapty/challenge.py
discapty/errors.py
discapty/fonts/Roboto-Regular.ttf
discapty/generators.py
discapty/py.typed
discapty/utils.py
discapty/wheezylib/__init__.py
discapty/wheezylib/bezier.py
discapty/wheezylib/image.py
discapty/wheezylib/README.md
discapty-2.2.0.dist-info/LICENSE
discapty-2.2.0.dist-info/METADATA
discapty-2.2.0.dist-info/WHEEL
discapty-2.2.0.dist-info/RECORD
