Metadata-Version: 2.1
Name: discapty
Version: 2.2.0
Summary: DisCapTy help you generate obfuscated images, leaving your code easy.
Home-page: https://github.com/Predeactor/DisCapTy
License: MIT
Author: Predeactor
Author-email: predeactor0@gmail.com
Requires-Python: >=3.8,<4.0
Classifier: Development Status :: 5 - Production/Stable
Classifier: Intended Audience :: Developers
Classifier: Intended Audience :: End Users/Desktop
Classifier: License :: OSI Approved :: MIT License
Classifier: Natural Language :: English
Classifier: Operating System :: OS Independent
Classifier: Programming Language :: Python :: 3
Classifier: Programming Language :: Python :: 3.8
Classifier: Programming Language :: Python :: 3.9
Classifier: Programming Language :: Python :: 3.10
Classifier: Programming Language :: Python :: 3.11
Classifier: Programming Language :: Python :: Implementation :: CPython
Classifier: Topic :: Multimedia :: Graphics
Classifier: Topic :: Security
Classifier: Topic :: Software Development :: Libraries :: Python Modules
Classifier: Topic :: Utilities
Classifier: Typing :: Typed
Requires-Dist: pillow (>=9.4.0,<10.0.0)
Requires-Dist: pydantic (>=2.5.2,<3.0.0)
Requires-Dist: pydantic-extra-types (>=2.2.0,<3.0.0)
Project-URL: Repository, https://github.com/Predeactor/DisCapTy
Project-URL: homepage, https://github.com/Predeactor/DisCapTy
